ctler.py
setup.py
ctler.egg-info/PKG-INFO
ctler.egg-info/SOURCES.txt
ctler.egg-info/dependency_links.txt
ctler.egg-info/requires.txt
ctler.egg-info/top_level.txt
ctler.egg-info/zip-safe