Metadata-Version: 1.0
Name: ctler
Version: 0.0.2
Summary: GrADS CTL reader.
Home-page: http://bitbucket.org/robertodealmeida/ctler/
Author: Roberto De Almeida
Author-email: roberto@dealmeida.net
License: MIT
Download-URL: http://cheeseshop.python.org/packages/source/p/ctler/ctler-0.0.2.tar.gz
Keywords: grads ctl data array math
Platform: UNKNOWN
Classifier: Development Status :: 3 - Alpha
Classifier: Environment :: Console
Classifier: Intended Audience :: Developers
Classifier: Intended Audience :: Science/Research
Classifier: License :: OSI Approved :: MIT License
Classifier: Operating System :: OS Independent
Classifier: Programming Language :: Python
Classifier: Topic :: Scientific/Engineering
Classifier: Topic :: Software Development :: Libraries :: Python Modules
